odoo/addons/base_cancel_confirm/README.rst
odoo/addons/base_cancel_confirm/__init__.py
odoo/addons/base_cancel_confirm/__manifest__.py
odoo/addons/base_cancel_confirm/i18n/base_cancel_confirm.pot
odoo/addons/base_cancel_confirm/i18n/nl.po
odoo/addons/base_cancel_confirm/model/__init__.py
odoo/addons/base_cancel_confirm/model/base_cancel_confirm.py
odoo/addons/base_cancel_confirm/readme/CONFIGURE.rst
odoo/addons/base_cancel_confirm/readme/CONTRIBUTORS.rst
odoo/addons/base_cancel_confirm/readme/DESCRIPTION.rst
odoo/addons/base_cancel_confirm/security/ir.model.access.csv
odoo/addons/base_cancel_confirm/static/description/icon.png
odoo/addons/base_cancel_confirm/static/description/index.html
odoo/addons/base_cancel_confirm/templates/cancel_confirm_template.xml
odoo/addons/base_cancel_confirm/tests/__init__.py
odoo/addons/base_cancel_confirm/tests/cancel_confirm_tester.py
odoo/addons/base_cancel_confirm/tests/test_cancel_confirm.py
odoo/addons/base_cancel_confirm/wizard/__init__.py
odoo/addons/base_cancel_confirm/wizard/cancel_confirm.py
odoo/addons/base_cancel_confirm/wizard/cancel_confirm.xml
odoo14_addon_base_cancel_confirm-14.0.1.1.0.dist-info/METADATA
odoo14_addon_base_cancel_confirm-14.0.1.1.0.dist-info/WHEEL
odoo14_addon_base_cancel_confirm-14.0.1.1.0.dist-info/top_level.txt
odoo14_addon_base_cancel_confirm-14.0.1.1.0.dist-info/RECORD
